mkdocs_mdpo_plugin/__init__.py
mkdocs_mdpo_plugin/config.py
mkdocs_mdpo_plugin/docs_helper.py
mkdocs_mdpo_plugin/extensions.py
mkdocs_mdpo_plugin/mdpo_events.py
mkdocs_mdpo_plugin/mdpo_utils.py
mkdocs_mdpo_plugin/mkdocs_utils.py
mkdocs_mdpo_plugin/plugin.py
mkdocs_mdpo_plugin/search_indexes.py
mkdocs_mdpo_plugin/translations.py
mkdocs_mdpo_plugin/utils.py
mkdocs_mdpo_plugin/custom_mdpo_sitemap/sitemap.xml
mkdocs_mdpo_plugin-0.0.27.dist-info/LICENSE
mkdocs_mdpo_plugin-0.0.27.dist-info/METADATA
mkdocs_mdpo_plugin-0.0.27.dist-info/WHEEL
mkdocs_mdpo_plugin-0.0.27.dist-info/entry_points.txt
mkdocs_mdpo_plugin-0.0.27.dist-info/top_level.txt
mkdocs_mdpo_plugin-0.0.27.dist-info/RECORD
