Metadata-Version: 2.1
Name: mkdocs-mdpo-plugin
Version: 0.0.27
Summary: Mkdocs plugin for translations using PO files.
Home-page: https://github.com/mondeja/mkdocs-mdpo-plugin
Author: Álvaro Mondéjar Rubio
Author-email: mondejar1994@gmail.com
License: BSD-3-Clause
Platform: UNKNOWN
Classifier: License :: OSI Approved :: BSD License
Classifier: Programming Language :: Python
Classifier: Programming Language :: Python :: 3
Classifier: Programming Language :: Python :: 3 :: Only
Classifier: Programming Language :: Python :: 3.6
Classifier: Programming Language :: Python :: 3.7
Classifier: Programming Language :: Python :: 3.8
Classifier: Programming Language :: Python :: 3.9
Classifier: Programming Language :: Python :: 3.10
Classifier: Programming Language :: Python :: Implementation :: CPython
Classifier: Programming Language :: Python :: Implementation :: PyPy
Classifier: Topic :: Documentation
Classifier: Topic :: Internet
Classifier: Topic :: Internet :: WWW/HTTP :: Dynamic Content
Classifier: Topic :: Software Development :: Documentation
Classifier: Topic :: Software Development :: Internationalization
Classifier: Topic :: Text Processing :: Markup :: Markdown
Requires-Python: >=3.6
License-File: LICENSE
Requires-Dist: mdpo (==0.3.85)
Requires-Dist: importlib-metadata ; python_version < "3.8"
Provides-Extra: dev
Requires-Dist: bump2version (==1.0.1) ; extra == 'dev'
Requires-Dist: flake8 (==4.0.1) ; extra == 'dev'
Requires-Dist: flake8-implicit-str-concat (==0.2.0) ; extra == 'dev'
Requires-Dist: flake8-print (==4.0.0) ; extra == 'dev'
Requires-Dist: isort (==5.10.1) ; extra == 'dev'
Requires-Dist: mkdocs (==1.2.3) ; extra == 'dev'
Requires-Dist: mkdocs-exclude (==1.0.2) ; extra == 'dev'
Requires-Dist: mkdocs-include-markdown-plugin (==3.3.0) ; extra == 'dev'
Requires-Dist: mkdocs-material (==7.1.2) ; extra == 'dev'
Requires-Dist: mkdocs-material-relative-language-selector (==1.1.4) ; extra == 'dev'
Requires-Dist: mkdocs-minify-plugin (==0.4.0) ; extra == 'dev'
Requires-Dist: mkdocs-minify-plugin (==0.5.0) ; extra == 'dev'
Requires-Dist: mkdocstrings (==0.15.2) ; extra == 'dev'
Requires-Dist: pre-commit (==2.17.0) ; extra == 'dev'
Requires-Dist: pre-commit-po-hooks (==1.7.3) ; extra == 'dev'
Requires-Dist: pymdown-extensions (<9) ; extra == 'dev'
Requires-Dist: pytest (==7.0.1) ; extra == 'dev'
Requires-Dist: pytest-cov (==3.0.0) ; extra == 'dev'
Requires-Dist: yamllint (==1.26.1) ; extra == 'dev'
Provides-Extra: doc
Requires-Dist: mkdocs (==1.2.3) ; extra == 'doc'
Requires-Dist: mkdocs-exclude (==1.0.2) ; extra == 'doc'
Requires-Dist: mkdocs-include-markdown-plugin (==3.3.0) ; extra == 'doc'
Requires-Dist: mkdocs-material (==7.1.2) ; extra == 'doc'
Requires-Dist: mkdocs-material-relative-language-selector (==1.1.4) ; extra == 'doc'
Requires-Dist: mkdocs-minify-plugin (==0.4.0) ; extra == 'doc'
Requires-Dist: mkdocstrings (==0.15.2) ; extra == 'doc'
Requires-Dist: pymdown-extensions (<9) ; extra == 'doc'
Provides-Extra: lint
Requires-Dist: flake8 (==4.0.1) ; extra == 'lint'
Requires-Dist: flake8-implicit-str-concat (==0.2.0) ; extra == 'lint'
Requires-Dist: flake8-print (==4.0.0) ; extra == 'lint'
Requires-Dist: isort (==5.10.1) ; extra == 'lint'
Requires-Dist: yamllint (==1.26.1) ; extra == 'lint'
Provides-Extra: test
Requires-Dist: mkdocs-exclude (==1.0.2) ; extra == 'test'
Requires-Dist: mkdocs-material (==7.1.2) ; extra == 'test'
Requires-Dist: mkdocstrings (==0.15.2) ; extra == 'test'
Requires-Dist: pre-commit-po-hooks (==1.7.3) ; extra == 'test'
Requires-Dist: pymdown-extensions (<9) ; extra == 'test'
Requires-Dist: pytest (==7.0.1) ; extra == 'test'
Requires-Dist: pytest-cov (==3.0.0) ; extra == 'test'
